welcome_overlords/__init__.py
welcome_overlords-1.0.dist-info/METADATA
welcome_overlords-1.0.dist-info/WHEEL
welcome_overlords-1.0.dist-info/licenses/LICENSE
welcome_overlords-1.0.dist-info/RECORD
