Metadata-Version: 2.1
Name: welcome_overlords
Version: 1.0
Summary: Welcome your new {function name} overlords by using this module's @Overlord.
Project-URL: Homepage, https://github.com/luap42/welcome_overlords
Project-URL: Issues, https://github.com/luap42/welcome_overlords/issues
Author-email: luap42 <me@luap42.de>
License-File: LICENSE
Classifier: License :: OSI Approved :: MIT License
Classifier: Operating System :: OS Independent
Classifier: Programming Language :: Python :: 3
Requires-Python: >=3.8
